stalowa_bukmacherska/__init__.py
stalowa_bukmacherska/stalowa_bukmacherska.py
stalowa_bukmacherska-0.4.0.dist-info/LICENSE
stalowa_bukmacherska-0.4.0.dist-info/METADATA
stalowa_bukmacherska-0.4.0.dist-info/WHEEL
stalowa_bukmacherska-0.4.0.dist-info/top_level.txt
stalowa_bukmacherska-0.4.0.dist-info/RECORD
