Metadata-Version: 2.1
Name: stalowa-bukmacherska
Version: 0.4.0
Summary: A description of your project
Home-page: https://github.com/your_username/your_project_name
Author: BARTOSZ RADOMSKI
Author-email: your_email@example.com
Classifier: Programming Language :: Python :: 3
Classifier: License :: OSI Approved :: MIT License
Classifier: Operating System :: OS Independent
Requires-Python: >=3.6
License-File: LICENSE
Requires-Dist: numpy>=1.20.0
Requires-Dist: matplotlib>=3.4.0
Requires-Dist: scipy>=1.6.0
Requires-Dist: scikit-learn>=0.24.0
